setup.py
jp_reading_alt.egg-info/PKG-INFO
jp_reading_alt.egg-info/SOURCES.txt
jp_reading_alt.egg-info/dependency_links.txt
jp_reading_alt.egg-info/requires.txt
jp_reading_alt.egg-info/top_level.txt
src/__init__.py
src/__version__.py
src/admin.py
src/alternation_model.py
src/explain_query.py
src/models.py
src/raw_reading_model.py
src/reading_database.py
src/reading_model.py
src/test_alternation_model.py
src/test_explain_query.py
src/test_reading_model.py
src/views.py