Metadata-Version: 1.0
Name: jp-reading-alt
Version: 0.1.1
Summary: Probabilistic reading error models for Japanese kanji.
Home-page: http://bitbucket.org/lars512/jp-reading-alt/
Author: Lars Yencken
Author-email: lljy@csse.unimelb.edu.au
License: BSD
Platform: UNKNOWN
